pft/__init__.py
pft/pft.py
pft-0.4.2.dist-info/LICENSE
pft-0.4.2.dist-info/WHEEL
pft-0.4.2.dist-info/METADATA
pft-0.4.2.dist-info/RECORD
